centrex_tlf_julia_extension/__init__.py
centrex_tlf_julia_extension/py.typed
centrex_tlf_julia_extension/lindblad_julia/__init__.py
centrex_tlf_julia_extension/lindblad_julia/generate_julia_code.py
centrex_tlf_julia_extension/lindblad_julia/julia_code_printer.py
centrex_tlf_julia_extension/lindblad_julia/julia_common.jl
centrex_tlf_julia_extension/lindblad_julia/ode_parameters.py
centrex_tlf_julia_extension/lindblad_julia/parse_julia_functions.py
centrex_tlf_julia_extension/lindblad_julia/utils_julia.py
centrex_tlf_julia_extension/lindblad_julia/utils_julia_functions.py
centrex_tlf_julia_extension/lindblad_julia/utils_julia_matrix.py
centrex_tlf_julia_extension/lindblad_julia/utils_julia_matrix_assemble.py
centrex_tlf_julia_extension/lindblad_julia/utils_setup.py
centrex_tlf_julia_extension/lindblad_julia/utils_solver.py
centrex_tlf_julia_extension/lindblad_julia/utils_solver_progress.py
centrex_tlf_julia_extension-0.4.3.dist-info/METADATA
centrex_tlf_julia_extension-0.4.3.dist-info/WHEEL
centrex_tlf_julia_extension-0.4.3.dist-info/licenses/LICENSE
centrex_tlf_julia_extension-0.4.3.dist-info/RECORD
