Metadata-Version: 2.4
Name: centrex-tlf-julia-extension
Version: 0.4.3
Summary: Extension for centrex-tlf to run OBE simulations in Julia
Project-URL: Repository, https://github.com/ograsdijk/CeNTREX-TlF-julia-extension
Author-email: ograsdijk <o.grasdijk@gmail.com>
License-Expression: MIT
License-File: LICENSE
Requires-Python: >=3.11
Requires-Dist: centrex-tlf>=0.1.8.4
Requires-Dist: juliacall>=0.9.30
Requires-Dist: psutil<6,>=5.9.4
